{
  "DisplayName": "GetJobProfile_Workday",
  "Tooltip": null,
  "HelpLink": null,
  "Color": null,
  "OriginalIconFileName": null,
  "Arguments": [
    {
      "Name": "in_strURL",
      "DisplayName": "in_strURL",
      "Category": null,
      "Tooltip": null,
      "Placeholder": null,
      "Widget": null,
      "IsRequired": false,
      "IsPrincipal": true,
      "DataSourceItems": null
    },
    {
      "Name": "out_strJobProfile",
      "DisplayName": "out_strJobProfile",
      "Category": null,
      "Tooltip": null,
      "Placeholder": null,
      "Widget": null,
      "IsRequired": false,
      "IsPrincipal": true,
      "DataSourceItems": null
    },
    {
      "Name": "in_strSEDetails",
      "DisplayName": "in_strSEDetails",
      "Category": null,
      "Tooltip": null,
      "Placeholder": null,
      "Widget": null,
      "IsRequired": false,
      "IsPrincipal": true,
      "DataSourceItems": null
    },
    {
      "Name": "in_strSEJobProfile",
      "DisplayName": "in_strSEJobProfile",
      "Category": null,
      "Tooltip": null,
      "Placeholder": null,
      "Widget": null,
      "IsRequired": false,
      "IsPrincipal": true,
      "DataSourceItems": null
    }
  ]
}